odoo/addons/website_sale_stock_list_preview/README.rst
odoo/addons/website_sale_stock_list_preview/__init__.py
odoo/addons/website_sale_stock_list_preview/__manifest__.py
odoo/addons/website_sale_stock_list_preview/controllers/__init__.py
odoo/addons/website_sale_stock_list_preview/controllers/main.py
odoo/addons/website_sale_stock_list_preview/i18n/es.po
odoo/addons/website_sale_stock_list_preview/i18n/it.po
odoo/addons/website_sale_stock_list_preview/i18n/website_sale_stock_list_preview.pot
odoo/addons/website_sale_stock_list_preview/readme/CONTRIBUTORS.md
odoo/addons/website_sale_stock_list_preview/readme/DESCRIPTION.md
odoo/addons/website_sale_stock_list_preview/readme/USAGE.md
odoo/addons/website_sale_stock_list_preview/static/description/icon.png
odoo/addons/website_sale_stock_list_preview/static/description/index.html
odoo/addons/website_sale_stock_list_preview/static/src/tests/tour.esm.js
odoo/addons/website_sale_stock_list_preview/tests/__init__.py
odoo/addons/website_sale_stock_list_preview/tests/test_ui.py
odoo/addons/website_sale_stock_list_preview/views/templates.xml
odoo_addon_website_sale_stock_list_preview-18.0.1.0.0.2.dist-info/METADATA
odoo_addon_website_sale_stock_list_preview-18.0.1.0.0.2.dist-info/WHEEL
odoo_addon_website_sale_stock_list_preview-18.0.1.0.0.2.dist-info/top_level.txt
odoo_addon_website_sale_stock_list_preview-18.0.1.0.0.2.dist-info/RECORD
